{
  "environment": "dev",
  "host": "localhost",
  "admin_url": "https://gestao-acelerados.vendittoapp.com",
  "api-port": "5000",
  "api-name": "Venditto Server",
  "database-ip": "localhost",
  "database-port": "5432",
  "database-name": "venditto-dev",
  "database-username": "postgres",
  "database-password": "postgres",
  "email1": "suporte@vendittoapp.com",
  "email1-password": "sev@gy07!",
  "email1-domain": "@godaddy.com",
  "email1-server": "smtpout.secureserver.net",
  "email1-port": "587",
  "email2": "",
  "email2-password": "",
  "email2-domain": "",
  "email2-server": "",
  "email2-port": "",
  "site": "",
  "database": "sqlite",
  "logPath": "../log.txt",
  "tempPath": ""
}